SafeCode/__init__.py
SafeCode/safecode.py
SafeCode/test.py
SafeCode/type.py
SafeCode-0.0.2.dist-info/METADATA
SafeCode-0.0.2.dist-info/WHEEL
SafeCode-0.0.2.dist-info/license
SafeCode-0.0.2.dist-info/top_level.txt
SafeCode-0.0.2.dist-info/RECORD
