Metadata-Version: 2.1
Name: SafeCode
Version: 0.0.2
Summary: A simple library for generating unique codes. Suitable if you want to generate unique codes and send them by sms to confirm your phone number, mail or other industry.
Home-page: https://github.com/SikWeet/SafeCode/tree/main
Author: Xpeawey
Author-email: girectx@gmail.com
Project-URL: GitHub, https://github.com/SikWeet
Keywords: safecode,safe code,code,pypi safecode,pypi safe code,pypi lib generation code,python generation code
Classifier: Programming Language :: Python :: 3.11
Classifier: License :: OSI Approved :: MIT License
Classifier: Operating System :: OS Independent
Requires-Python: >=3.6
License-File: license
Requires-Dist: xtools-py >=0.1.1
